getgithubrepourls/__init__.py
getgithubrepourls-1.0.2.dist-info/METADATA
getgithubrepourls-1.0.2.dist-info/WHEEL
getgithubrepourls-1.0.2.dist-info/top_level.txt
getgithubrepourls-1.0.2.dist-info/RECORD
