Metadata-Version: 2.1
Name: getgithubrepourls
Version: 1.0.2
Author: emresvd
Classifier: Development Status :: 5 - Production/Stable
Classifier: Intended Audience :: Developers
Classifier: Natural Language :: English
Classifier: Programming Language :: Python :: 3.7
Classifier: Topic :: Software Development :: Libraries :: Python Modules
Requires-Dist: beautifulsoup4 (==4.11.1)
Requires-Dist: requests (==2.28.1)
